[
    {
        "data": {
            "category": "invocDruid",
            "costStamina": 8,
            "effect": "Кипящая кровь заставляет животное или неразумное чудовище в пределах дистанции заклинания разозлиться на цель. Это существо будет пытаться напасть на цель, пока действие заклинания не закончится.",
            "source": "core",
            "specData": {
                "DistantionType": "accurate",
                "DistantionValue": 8,
                "LevelType": "newbie",
                "defence": "willx3",
                "duration": "1d10 раундов"
            }
        },
        "img": "systems/TheWitcherRPG/assets/Spells/Invocations/Druid/BoilingBlood.png",
        "name": "Кипящая кровь",
        "type": "spell"
    },
    {
        "data": {
            "category": "invocDruid",
            "costStamina": 999999,
            "effect": "Вызывает у цели болезнь, которая проявляется по-разному в зависимости от затраченного количества очков Выносливости. 2 очка заставят цель согнуться в приступе кашля и ошеломят её. 4 очка вызовут у цели сильную тошноту, дезориентируя её. Затратив 6 очков, вы нашлёте на цель серьёзную болезнь, действующую аналогично отравлению. Эффект инвокации заканчивается, когда цель успешно проходит проверку Стойкости со СЛ, равной проверке сотворения инвокации.",
            "source": "core",
            "specData": {
                "DistantionType": "accurate",
                "DistantionValue": 8,
                "LevelType": "newbie",
                "defence": "blocking",
                "duration": "Проверка стойкости завершает"
            }
        },
        "img": "systems/TheWitcherRPG/assets/Spells/Invocations/Druid/CursedIllness.png",
        "name": "Проклятая болезнь",
        "type": "spell"
    },
    {
        "data": {
            "category": "invocDruid",
             "costStamina": 1,
            "effect": "Заклинатель получает бонус +3 к Выживанию в дикой природе при обращении с животными. В качестве альтернативы заклинание может успокоить одно животное, если результат проверки Сотворения заклинаний выше Воли животного х 3.",
            "source": "core",
            "specData": {
                "DistantionType": "selfacc",
                "DistantionValue": 5,
                "LevelType": "newbie",
                "defence": "willx3",
                "duration": "1d6 часов"
            }
        },
        "img": "systems/TheWitcherRPG/assets/Spells/Invocations/Druid/FriendToWildKind.png",
        "name": "Друг животных",
        "type": "spell"
    },
    {
        "data": {
            "category": "invocDruid",
            "costStamina": 999999,
            "effect": "Дар природы выращивает небольшое количество съедобных растений на любой почве. Растений достаточно, чтобы насытить на 1 день количество персон, равное числу затраченных очков Выносливости.",
            "source": "core",
            "specData": {
                "DistantionType": "accurate",
                "DistantionValue": 2,
                "LevelType": "newbie",
                "defence": "no",
                "duration": "Мгновенное"
            }
        },
        "img": "systems/TheWitcherRPG/assets/Spells/Invocations/Druid/NatureGift.png",
        "name": "Дар природы",
        "type": "spell"
    },
    {
        "data": {
            "category": "invocDruid",
            "costStamina": 2,
            "effect": "Взор природы позволяет видеть существ, не свойственных этому измерению. Заклинатель может разглядеть чудовищ в пределах 50 метров даже сквозь препятствия. Увиденные таким образом чудовища кажутся светящимися.",
            "source": "core",
            "specData": {
                "DistantionType": "self",
                "DistantionValue": 0,
                "LevelType": "newbie",
                "defence": "no",
                "duration": "Активное (1 Выносливости)"
            }
        },
        "img": "systems/TheWitcherRPG/assets/Spells/Invocations/Druid/NatureSight.png",
        "name": "Взор природы",
        "type": "spell"
    },
    {
        "data": {
            "category": "invocDruid",
            "costStamina": 2,
            "effect": "Начертание этого символа позволяет скрыть 3-метровую зону с помощью листьев, веток и прочих природных деталей, создавая эффект полной невидимости. Это даёт бонус +5 к Скрытности, но всякий, кто находится в этой зоне, не может двинуться. Чтобы снять маскировку, заклинание нужно повторить. Можно срезать заросли, нанеся им 10 урона.",
            "source": "core",
            "specData": {
                "DistantionType": "self",
                "DistantionValue": 0,
                "LevelType": "newbie",
                "defence": "no",
                "duration": "До рассеивания"
            }
        },
        "img": "systems/TheWitcherRPG/assets/Spells/Invocations/Druid/SigilOfTheHidden.png",
        "name": "Символ скрытого",
        "type": "spell"
    },
    {
        "data": {
            "category": "invocDruid",
            "costStamina": 5,
            "effect": "Ускоряет естественный процесс регенерации цели, восстанавливая ей 3 ПЗ за раунд. Это благословение можно использовать несколько раз для исцеления критического ранения, но в таком случае оно не восстанавливает ПЗ.",
            "source": "core",
            "specData": {
                "DistantionType": "accurate",
                "DistantionValue": 2,
                "LevelType": "prentice",
                "defence": "no",
                "duration": "Активное (3 Выносливости)"
            }
        },
        "img": "systems/TheWitcherRPG/assets/Spells/Invocations/Druid/BlessingOfHealing.png",
        "name": "Благословение исцеления",
        "type": "spell"
    },
    {
        "data": {
            "category": "invocDruid",
            "costStamina": 6,
            "effect": "Пробуждает внутренние резервы цели, что даёт бонус +2 к урону в ближнем бою и штраф -2 к Интелекту на время действия заклинания.",
            "source": "core",
            "specData": {
                "DistantionType": "accurate",
                "DistantionValue": 5,
                "LevelType": "prentice",
                "defence": "magic",
                "duration": "2d6 раундов"
            }
        },
        "img": "systems/TheWitcherRPG/assets/Spells/Invocations/Druid/PrimalReservoid.png",
        "name": "Животная сила",
        "type": "spell"
    },
    {
        "data": {
            "category": "invocDruid",
            "costStamina": 4,
            "effect": "Позволяет в радиусе действия заклинания увидеть нити жизни, связующие всё живое. С помощью Нитей жизни можно определить количество оставшихся ПЗ и любые полученные критические ранения у тех, кого видит заклинатель.",
            "source": "core",
            "specData": {
                "DistantionType": "accurate",
                "DistantionValue": 10,
                "LevelType": "prentice",
                "defence": "no",
                "duration": "Активное (2 Выносливости)"
            }
        },
        "img": "systems/TheWitcherRPG/assets/Spells/Invocations/Druid/ThreadsOflife.png",
        "name": "Нити жизни",
        "type": "spell"
    },
    {
        "data": {
            "category": "invocDruid",
            "costStamina": 12,
            "effect": "Позволяет превратить ближайшее небольшое дерево в голема. Он служит заклинателю всё время действия заклинания, а потом превращается обратно в дерево. Если убить голема, с него можно получить только 2d10 древесины. По остальным параметрам этот деревянный голем аналогичен нормальному",
            "source": "core",
            "specData": {
                "DistantionType": "accurate",
                "DistantionValue": 10,
                "LevelType": "master",
                "defence": "no",
                "duration": "1d10 раундов"
            }
        },
        "img": "systems/TheWitcherRPG/assets/Spells/Invocations/Druid/ShapeNature.png",
        "name": "Управление природой",
        "type": "spell"
    },
    {
        "data": {
            "category": "invocDruid",
            "costStamina": 10,
            "effect": "Песнь небес меняет погоду вокруг заклинателя. Погоду можно изменить на: ясную (нет модификаторов), облачную (мало солнечного света), ливень (гасит огонь), штормовой ветер (-2 к Ловкости для дистанционных атак) или грозу (шанс 35 % попасть под удар молнии, аналогично заклинанию Гроза).",
            "source": "core",
            "specData": {
                "DistantionType": "accurate",
                "DistantionValue": 50,
                "LevelType": "master",
                "defence": "no",
                "duration": "Активное (5 Выносливости)"
            }
        },
        "img": "systems/TheWitcherRPG/assets/Spells/Invocations/Druid/SongOfTheSky.png",
        "name": "Песнь небес",
        "type": "spell"
    }
]